<?xml version="1.0" encoding="utf-8"?>
<selector xmlns:android="http://schemas.android.com/apk/res/android">

    <item android:state_focused="true">
        <shape android:shape="rectangle">
            <corners android:radius="120dp"/>
            <solid android:color="@color/try_button_hover"/>
        </shape>
    </item>

    <item android:state_hovered="true">
        <shape android:shape="rectangle">
            <corners android:radius="100dp"/>
            <solid android:color="@color/try_button_hover"/>
        </shape>
    </item>

    <item>
        <shape android:shape="rectangle">
            <corners android:radius="120dp"/>
            <solid android:color="@color/try_button"/>
        </shape>
    </item>

</selector>